tencoin_core/__init__.py
tencoin_core/__version__.py
tencoin_core/constants.py
tencoin_core/utils.py
tencoin_core/wallet.py
tencoin_core/keys/bip32.py
tencoin_core/keys/bip39.py
tencoin_core/keys/bip84.py
tencoin_core/keys/ec.py
tencoin_core/keys/wordlist.py
tencoin_core/rpc/__init__.py
tencoin_core/rpc/client.py
tencoin_core/rpc/exceptions.py
tencoin_core/transaction/__init__.py
tencoin_core/transaction/address.py
tencoin_core/transaction/builder.py
tencoin_core/transaction/core.py
tencoin_core/transaction/fee.py
tencoin_core/transaction/signer.py
tencoin_core-0.1.0.dist-info/METADATA
tencoin_core-0.1.0.dist-info/WHEEL
tencoin_core-0.1.0.dist-info/top_level.txt
tencoin_core-0.1.0.dist-info/RECORD
