Metadata-Version: 2.4
Name: tencoin-core
Version: 0.1.0
Summary: Official Python library for Tencoin – HD wallets, SegWit, BIP39, RPC client
Author: Tencoin Development Team
License: MIT
Project-URL: Homepage, https://github.com/TenCoin-crypto/TenCoin
Project-URL: Repository, https://github.com/TenCoin-crypto/TenCoin
Project-URL: Issues, https://github.com/TenCoin-crypto/TenCoin/issues
Project-URL: Documentation, https://tencoin-core.readthedocs.io
Keywords: tencoin,blockchain,cryptocurrency,hd-wallet,bip39,segwit,rpc
Classifier: Development Status :: 4 - Beta
Classifier: Intended Audience :: Developers
Classifier: License :: OSI Approved :: MIT License
Classifier: Operating System :: OS Independent
Classifier: Programming Language :: Python :: 3
Classifier: Programming Language :: Python :: 3.8
Classifier: Programming Language :: Python :: 3.9
Classifier: Programming Language :: Python :: 3.10
Classifier: Programming Language :: Python :: 3.11
Classifier: Programming Language :: Python :: 3.12
Classifier: Topic :: Software Development :: Libraries :: Python Modules
Classifier: Topic :: Utilities
Requires-Python: >=3.8
Requires-Dist: ecdsa>=0.18.0
Requires-Dist: requests>=2.28.0
Requires-Dist: bech32>=1.2.0
Provides-Extra: dev
Requires-Dist: pytest>=7.0; extra == "dev"
Requires-Dist: pytest-cov; extra == "dev"
Requires-Dist: black; extra == "dev"
Requires-Dist: ruff; extra == "dev"
Provides-Extra: async
Requires-Dist: aiohttp>=3.8.0; extra == "async"
Provides-Extra: mnemonic
Requires-Dist: mnemonic>=0.20; extra == "mnemonic"
